[
    {
      "id": "623e8047315822d0fcc7e581",
      "img": "https://www.vocesimposibles.com/images/h/handbags%20for%20ladies-065qyr.jpg",
      "price": 225,
      "name": "New Stylish Handbags For Girls"
    },
    {
      "id": "623e8047647acebbf86e5f2d",
      "img": "https://m.media-amazon.com/images/I/71DQ9y0WWCL.jpg",
      "price": 112,
      "name": "2022 Spring New Fashion Women Shoulder"
    },
    {
      "id": "623e80472dfb2ba6050cdfb6",
      "img": "https://i.ebayimg.com/images/g/iXgAAOSwrVRfsZc4/s-l300.jpg",
      "price": 181,
      "name": "New Fashion Women Handbags Ladie"
    },
    {
      "id": "623e80472915eafc9f99a6ce",
      "img": "http://wassupblog.com/top-shopping/wp-content/uploads/2016/01/ZOOLER-bags-handbags-women-famous-brands-shoulder-messenger-bags-genuine-leather-handbags-Boston-pillow-Serpentine-grain.jpg",
      "price": 106,
      "name": "2022 New Spring And Summer"
    },
    {
      "id": "623e80476e968ffe98b8cb83",
      "img": "https://img10.joybuy.com/N0/s560x560_jfs/t23851/65/198296022/96680/88f8e436/5b286e56Nd495e192.jpg.dpg",
      "price": 292,
      "name": "Design Ladies Hand Bag - F604 -"
    },
    {
      "id": "623e80479c1586b2d26df2e2",
      "img": "https://ae01.alicdn.com/kf/HTB1GH7eXDjxK1Rjy0Fnxh5BaFXaE/Ladies-Shoulder-Bags-New-Cute-Type-PU-High-Quality-Hot-Sale-Girls-Diagonal-bag-Color-Matching.jpeg_q50.jpeg",
      "price": 283,
      "name": "Ladies Shoulder Bags New Cute"
    },
    {
      "id": "623e8047fc96731c28d02be2",
      "img": "https://i.pinimg.com/564x/b5/d5/d8/b5d5d8437749006b806a69953fc40d44.jpg",
      "price": 285,
      "name": "New Design Ladies Leather Handbag"
    },

    {
        "id": "623e8047fc96731c28d02be1",
        "img": "https://i.pinimg.com/originals/ba/aa/1b/baaa1b07676f09bfb16fce5cfc01435e.jpg",
        "price": 285,
        "name": "Leather Hand Bag for Women"
      },

      {
        "id": "623e8047fc96731c28d02be0",
        "img": "https://i.pinimg.com/736x/4e/7c/11/4e7c11ffc9980d46b2b87440adb21794.jpg",
        "price": 285,
        "name": "Fashionable bags for women"
      }
  ]